{
  "image" : "https://m.media-amazon.com/images/I/61sPrbSIr-L._SX300_SY300_QL70_FMwebp_.jpg",
  "form" : "Import",
  "price" : "$15.94",
  "cat" : "Audio CD",
  "description" : "Out of print in the U.S.! Though he'd been a professional musician for over two decades, Outrider was the first official solo album by former Led Zeppelin guitar legend. The album showcases Page's unique style that charmed the pants off of Zep fans for a decade. Speaking of Zep, both Robert Plant and Jason Bonham (John's son) make appearances on the album alongside Chris Farlowe, John Miles, Tony Franklin and others. Features nine tracks including 'Wasting My Time', 'The Only One' and the beautiful 'Emerald Eyes'. Universal.",
  "details" : "Product details Is Discontinued By Manufacturer ‏ : ‎ No Language ‏ : ‎ English Product Dimensions ‏ : ‎ 5.63 x 5.08 x 0.39 inches; 3.39 ounces Manufacturer ‏ : ‎ Universal I.S. Item model number ‏ : ‎ Outrider Original Release Date ‏ : ‎ 1996 SPARS Code ‏ : ‎ DDD Date First Available ‏ : ‎ December 7, 2006 Label ‏ : ‎ Universal I.S. ASIN ‏ : ‎ B000000OYQ Number of discs ‏ : ‎ 1 Best Sellers Rank: #48,605 in CDs & Vinyl (See Top 100 in CDs & Vinyl) #77 in Guitar Gods #276 in British Invasion Rock #1,107 in Blues Rock (CDs & Vinyl) Customer Reviews: 4.4 4.4 out of 5 stars 320 ratings",
  "title" : "Outrider"
}