{
  "image" : "https://m.media-amazon.com/images/I/51mQNF+bPZL._SY300_.jpg",
  "price" : "$16.95",
  "cat" : "Audio CD",
  "details" : "Product details Is Discontinued By Manufacturer ‏ : ‎ No Product Dimensions ‏ : ‎ 5.5 x 5.5 x 0.25 inches; 2.5 ounces Manufacturer ‏ : ‎ Polygram Records Item model number ‏ : ‎ 43168-88214 Date First Available ‏ : ‎ January 17, 2007 Label ‏ : ‎ Polygram Records ASIN ‏ : ‎ B000001F7V Number of discs ‏ : ‎ 1 Best Sellers Rank: #354,787 in CDs & Vinyl (See Top 100 in CDs & Vinyl) #3,954 in Funk (CDs & Vinyl) #12,713 in Soul (CDs & Vinyl) #165,179 in Pop (CDs & Vinyl) Customer Reviews: 4.7 4.7 out of 5 stars 91 ratings",
  "title" : "Celebrate"
}