{
  "image" : "https://m.media-amazon.com/images/I/81XyLpv2YLL._SX425_.jpg",
  "price" : "$16.61",
  "cat" : "Audio CD",
  "description" : "CD",
  "details" : "Product details Is Discontinued By Manufacturer ‏ : ‎ No Product Dimensions ‏ : ‎ 5.55 x 4.92 x 0.47 inches; 3.25 ounces Manufacturer ‏ : ‎ Touch & Go Records Original Release Date ‏ : ‎ 1994 Date First Available ‏ : ‎ December 10, 2006 Label ‏ : ‎ Touch & Go Records ASIN ‏ : ‎ B0000019KU Number of discs ‏ : ‎ 1 Best Sellers Rank: #37,523 in CDs & Vinyl (See Top 100 in CDs & Vinyl) #697 in Progressive Rock #778 in Indie Rock #3,591 in Alternative Rock (CDs & Vinyl) Customer Reviews: 4.8 4.8 out of 5 stars 109 ratings",
  "title" : "At Action Park"
}